{
    "PDS-31p2050-Plausible": {
		"emissions_reduced_per_unit_area": 13.8339291982872,
		"direct_emissions_are_annual" : false,
        "growth_rate_of_ocean_degradation": 1.0,
		"delay_impact_of_protection_by_one_year": true,
		"delay_regrowth_of_degraded_land_by_one_year": false,
		"use_adoption_for_carbon_sequestration_calculation": false,
		"current_area_world": 490.0,
		"future_ref_area": 490.0,
		"future_pds_area": 490.0,
		"total_area_as_of_period": 2014,
		"change_per_period": 0.0,
        "current_adoption_world": 0.0,
        "pds_scenario_name": "AverageOfAllCustomPDSScenarios",
        "ref_scenario_name": "",
        "scenario_timestamp": "2021-04-12T10:55:59",
        "scenario_description": "Average of all adoptions"
    },
    "PDS-42p2050-Drawdown": {
		"emissions_reduced_per_unit_area": 13.8339291982872,
		"direct_emissions_are_annual" : false,
        "growth_rate_of_ocean_degradation": 1.0,
		"delay_impact_of_protection_by_one_year": true,
		"delay_regrowth_of_degraded_land_by_one_year": false,
		"use_adoption_for_carbon_sequestration_calculation": false,
		"current_area_world": 490.0,
		"future_ref_area": 490.0,
		"future_pds_area": 490.0,
		"total_area_as_of_period": 2014,
		"change_per_period": 0.0,
        "current_adoption_world": 0.0,
        "pds_scenario_name": "HighOfAllCustomPDSScenarios",
        "ref_scenario_name": "",
        "scenario_timestamp": "2021-04-12T10:56:35",
        "scenario_description": "High of all adoptions"
    },
    "PDS-48p2050-Optimum": {
		"emissions_reduced_per_unit_area": 13.8339291982872,
		"direct_emissions_are_annual" : false,
        "growth_rate_of_ocean_degradation": 1.0,
		"delay_impact_of_protection_by_one_year": true,
		"delay_regrowth_of_degraded_land_by_one_year": false,
		"use_adoption_for_carbon_sequestration_calculation": false,
		"current_area_world": 490.0,
		"future_ref_area": 490.0,
		"future_pds_area": 490.0,
		"total_area_as_of_period": 2014,
		"change_per_period": 0.0,
        "current_adoption_world": 0.0,
        "pds_scenario_name": "90pctTOAProtectedBy2050",
        "ref_scenario_name": "",
        "scenario_timestamp": "2021-04-12T10:58:40",
        "scenario_description": "The highest adoption scenario"
    }
}