{
    "name": "PDS3-73p2050-May2020",
    "solution_category": "reduction",
    "vmas": "VMAs",
    "description": "OECD follows growth rate set as an EU goal in 1995 (demonstrated to be achievable  by Austria), in which landfilled organic waste is reduced to 35% of 1995 levels in 20 years. All other regions increase at the same rate of increase per year. Max limit to adoption set at 73%, what OECD would be after the 20 years, and what Austria's current composting rate is. ",
    "report_start_year": 2020,
    "report_end_year": 2050,
    "conv_2014_cost": {
        "value": 272081195.3789954,
        "statistic": ""
    },
    "conv_first_cost_efficiency_rate": 0.0,
    "conv_lifetime_capacity": {
        "value": 30.0,
        "statistic": ""
    },
    "conv_avg_annual_use": {
        "value": 1.0,
        "statistic": ""
    },
    "conv_var_oper_cost_per_funit": {
        "value": 139157285.575107,
        "xls cell formula": "H101+D192"
    },
    "conv_fixed_oper_cost_per_iunit": {
        "value": 0.0,
        "statistic": ""
    },
    "conv_fuel_cost_per_funit": 0.0,
    "pds_2014_cost": {
        "value": 139720139.19252658,
        "statistic": ""
    },
    "ref_2014_cost": {
        "value": 139720139.19252658,
        "statistic": ""
    },
    "soln_first_cost_efficiency_rate": 0.0,
    "soln_first_cost_below_conv": true,
    "soln_lifetime_capacity": {
        "value": 30.0,
        "statistic": ""
    },
    "soln_avg_annual_use": {
        "value": 1.0,
        "statistic": ""
    },
    "soln_var_oper_cost_per_funit": {
        "value": 139847635.319605,
        "xls cell formula": "H116+D192"
    },
    "soln_fixed_oper_cost_per_iunit": {
        "value": 0.0,
        "statistic": ""
    },
    "soln_fuel_cost_per_funit": 0.0,
    "npv_discount_rate": 0.064,
    "conv_annual_energy_used": {
        "value": 0.0,
        "statistic": ""
    },
    "soln_energy_efficiency_factor": {
        "value": 0.0,
        "statistic": ""
    },
    "soln_annual_energy_used": {
        "value": 0.0,
        "statistic": ""
    },
    "conv_fuel_consumed_per_funit": {
        "value": 0.0,
        "statistic": ""
    },
    "soln_fuel_efficiency_factor": {
        "value": 0.0,
        "statistic": ""
    },
    "conv_fuel_emissions_factor": {
        "value": 0.0,
        "statistic": ""
    },
    "soln_fuel_emissions_factor": {
        "value": 0.0,
        "statistic": ""
    },
    "conv_emissions_per_funit": {
        "value": 559239.425,
        "statistic": ""
    },
    "soln_emissions_per_funit": {
        "value": 160128.9512774807,
        "statistic": ""
    },
    "conv_indirect_co2_per_unit": {
        "value": 0.0,
        "statistic": ""
    },
    "soln_indirect_co2_per_iunit": {
        "value": 0.0,
        "statistic": ""
    },
    "conv_indirect_co2_is_iunits": false,
    "ch4_co2_per_funit": {
        "value": 0.0,
        "statistic": ""
    },
    "ch4_is_co2eq": false,
    "n2o_co2_per_funit": {
        "value": 0.0,
        "statistic": ""
    },
    "n2o_is_co2eq": false,
    "co2eq_conversion_source": "AR5 with feedback",
    "emissions_use_co2eq": true,
    "emissions_grid_source": "Meta-Analysis",
    "emissions_grid_range": "Mean",
    "source_until_2014": "Organic Fraction of MSW - From Waste TAM",
    "ref_source_post_2014": "Organic Fraction of MSW - From Waste TAM",
    "pds_source_post_2014": "Drawdown TAM: Organic Fraction of MSW - Waste TAM",
    "ref_base_adoption": {
        "World": 131.540502616249,
        "OECD90": 63.0763380296636,
        "Eastern Europe": 2.88637729277583,
        "Asia (Sans Japan)": 60.0288227406692,
        "Middle East and Africa": 5.31812672525022,
        "Latin America": 0.230837827890141,
        "China": 4.6019002576339,
        "India": 42.2618412201257,
        "EU": 39.82045,
        "USA": 22.77
    },
    "soln_pds_adoption_basis": "Fully Customized PDS",
    "soln_pds_adoption_regional_data": false,
    "pds_adoption_final_percentage": {
        "World": 0.0,
        "OECD90": 0.0,
        "Eastern Europe": 0.0,
        "Asia (Sans Japan)": 0.0,
        "Middle East and Africa": 0.0,
        "Latin America": 0.0,
        "China": 0.0,
        "India": 0.0,
        "EU": 0.0,
        "USA": 0.0
    },
    "soln_pds_adoption_custom_name": "PDS3-Austria Growth Path, May 2020",
    "soln_ref_adoption_basis": "Default",
    "soln_ref_adoption_regional_data": false
}